mkdocs_obsidian_excalidraw/__init__.py
mkdocs_obsidian_excalidraw/plugin.py
mkdocs_obsidian_excalidraw/update_page.py
mkdocs_obsidian_excalidraw_plugin-0.1.1.dist-info/LICENSE
mkdocs_obsidian_excalidraw_plugin-0.1.1.dist-info/METADATA
mkdocs_obsidian_excalidraw_plugin-0.1.1.dist-info/WHEEL
mkdocs_obsidian_excalidraw_plugin-0.1.1.dist-info/entry_points.txt
mkdocs_obsidian_excalidraw_plugin-0.1.1.dist-info/top_level.txt
mkdocs_obsidian_excalidraw_plugin-0.1.1.dist-info/RECORD
