Metadata-Version: 2.2
Name: mkdocs-obsidian-excalidraw-plugin
Version: 0.1.1
Summary: A MkDocs plugin
Home-page: 
Author: Peter Heiss
Author-email: peter.heiss@uni-muenster.de
License: MIT
Keywords: mkdocs,excalidraw,obsidian
Classifier: Development Status :: 4 - Beta
Classifier: Intended Audience :: Developers
Classifier: Intended Audience :: Information Technology
Classifier: License :: OSI Approved :: MIT License
Classifier: Programming Language :: Python
Classifier: Programming Language :: Python :: 3 :: Only
Classifier: Programming Language :: Python :: 3.4
Classifier: Programming Language :: Python :: 3.5
Classifier: Programming Language :: Python :: 3.6
Classifier: Programming Language :: Python :: 3.7
Requires-Python: >=3.0
License-File: LICENSE
Requires-Dist: mkdocs>=1.6.1
Dynamic: author
Dynamic: author-email
Dynamic: classifier
Dynamic: description
Dynamic: description-content-type
Dynamic: keywords
Dynamic: license
Dynamic: requires-dist
Dynamic: requires-python
Dynamic: summary
